{
  "string": [
    {
      "name": "module_desc",
      "value": "模块描述"
    },
    {
      "name": "EntryAbility_desc",
      "value": "description"
    },
    {
      "name": "EntryAbility_label",
      "value": "OmniUI"
    },
    {
      "name": "multi_guide_page",
      "value": "多页引导页"
    },
    {
      "name": "just_use_it_simply",
      "value": "简单使用"
    },
    {
      "name": "current_index",
      "value": "当前引导页index： "
    },
    {
      "name": "guide_page_switching",
      "value": "引导页切换： "
    }
  ]
}